task_tracker/__init__.py
task_tracker/cli.py
task_tracker/manager.py
task_tracker/utils.py
daily_tasktrack-0.1.0.dist-info/METADATA
daily_tasktrack-0.1.0.dist-info/WHEEL
daily_tasktrack-0.1.0.dist-info/entry_points.txt
daily_tasktrack-0.1.0.dist-info/top_level.txt
daily_tasktrack-0.1.0.dist-info/RECORD
