Metadata-Version: 2.4
Name: daily-tasktrack
Version: 0.1.0
Summary: Simple YAML task time tracker
Author-email: Evgeni Roif <eugene@roifgroup.com>
Requires-Python: >=3.7
